esds/__init__.py
esds/__main__.py
esds/debug.py
esds/node.py
esds/platform.py
esds/rcode.py
esds/simulator.py
esds/helpers/__init__.py
esds/helpers/wireless_area.py
esds/plugins/__init__.py
esds/plugins/node_plugin.py
esds/plugins/operating_states.py
esds/plugins/power_states.py
esds-0.0.8.dist-info/LICENSE
esds-0.0.8.dist-info/METADATA
esds-0.0.8.dist-info/WHEEL
esds-0.0.8.dist-info/entry_points.txt
esds-0.0.8.dist-info/top_level.txt
esds-0.0.8.dist-info/RECORD
