Metadata-Version: 2.1
Name: esds
Version: 0.0.8
Summary: An Extensible Simulator for Distributed Systems
Keywords: simulator,distributed systems,cyber-physical,systems,network,wireless,wired
License-File: LICENSE
Requires-Dist: numpy
Requires-Dist: pyyaml
